async_translate/__init__.py
async_translate/_version.py
async_translate/abc.py
async_translate/async_translate.py
async_translate/caseinsensitivedict.py
async_translate/errors.py
async_translate/providers/__init__.py
async_translate/providers/azure/__init__.py
async_translate/providers/azure/azure.py
async_translate/providers/azure/errors.py
async_translate/providers/google/__init__.py
async_translate/providers/google/google.py
async_translate-1.1.3.dist-info/LICENSE
async_translate-1.1.3.dist-info/METADATA
async_translate-1.1.3.dist-info/WHEEL
async_translate-1.1.3.dist-info/top_level.txt
async_translate-1.1.3.dist-info/RECORD
