Metadata-Version: 2.1
Name: async-translate
Version: 1.1.3
Summary: Multi-provider async translate API
Home-page: https://github.com/Memotic/async-translate
Author: William Hatcher
Author-email: william@memotic.net
License: MIT
Platform: UNKNOWN
Classifier: Programming Language :: Python :: 3
Classifier: License :: OSI Approved :: MIT License
Classifier: Operating System :: OS Independent
Classifier: Intended Audience :: Developers
Classifier: Natural Language :: English
Requires-Python: >=3.8
Provides-Extra: azure
Requires-Dist: aiocache ; extra == 'azure'
Requires-Dist: aiohttp ; extra == 'azure'
Requires-Dist: ujson ; extra == 'azure'
Requires-Dist: msgpack ; extra == 'azure'
Requires-Dist: aiohttp-retry ; extra == 'azure'
Provides-Extra: google
Requires-Dist: google-cloud-translate ~=3.6.1 ; extra == 'google'
Requires-Dist: aiocache ; extra == 'google'
